piplink/__init__.py
piplink/upload.py
piplink-2.2.4.dist-info/LICENSE
piplink-2.2.4.dist-info/METADATA
piplink-2.2.4.dist-info/WHEEL
piplink-2.2.4.dist-info/entry_points.txt
piplink-2.2.4.dist-info/top_level.txt
piplink-2.2.4.dist-info/RECORD
