Metadata-Version: 2.1
Name: piplink
Version: 2.2.4
Summary: A simple package for uploading packages to PyPI
Home-page: https://mrfidal.in/basic-pip-package/piplink
Author: Fidal
Author-email: mrfidal@proton.me
License-File: LICENSE
Requires-Dist: requests
Requires-Dist: requests-toolbelt
